Workbook

Sheet はじめに
A1: Claude×Excel 練習用シート
A2: プロンプト集（PDF）とセットで使ってください。データはすべて架空のダミーです。
A4: シート | B4: 練習できること | C4: 対応するプロンプト（PDF）
A5: 売上表 | B5: 月別・取引先別の集計、商品マスタからの単価の取り出し、合計が合わない原因さがし | C5: No.1〜3、6〜8
A6: 商品マスタ | B6: VLOOKUP / XLOOKUP で売上表とつなぐ | C6: No.3、6
A7: 経費精算 | B7: 科目別の集計、重複・異常値・領収書もれのチェック | C7: No.2、15、16
A8: 取引先リスト | B8: 表記ゆれ（株式会社／(株)／全角半角など）の統一、重複チェック | C8: No.10〜12
A9: 請求と入金 | B9: 請求一覧と入金一覧の照合（入金もれ・金額ちがい） | C9: No.14
A12: 色の意味
B13: 黄色のセル … 数式を入れて練習する場所です。自由に書きかえてOK。
B14: ピンクのセル … わざと入れた「ミス」です。カーソルを合わせるとヒントが出ます。
A15: 使い方
B16: ① PDFのプロンプトをコピーして、［ ］の部分をこのシートの内容に書きかえる
B17: ② シートの表をClaudeに貼り付ける（またはファイルごと添付する）
B18: ③ 返ってきた数式を黄色のセルに入れて、結果を確かめる
A19: 注意
B20: 実際の業務データを使うときは、会社のルールを確認し、取引先名・個人名などを伏せてから使ってください。
A23: 作成: @mikan_keiri

Sheet 商品マスタ
A1: 商品マスタ
A2: 売上表の「商品コード」から商品名・単価を取り出す練習用です。
A4: 商品コード | B4: 商品名 | C4: 単価
A5: A-101 | B5: A4コピー用紙（500枚×5冊） | C5: 2800
A6: A-102 | B6: ボールペン 黒（10本） | C6: 980
A7: A-103 | B7: クリアファイル（100枚） | C7: 1500
A8: B-201 | B8: トナーカートリッジ | C8: 12800
A9: B-202 | B9: ラベルシール（20シート） | C9: 1200
A10: C-301 | B10: デスクライト | C10: 6400

Sheet 売上表
A1: 売上表（2026年8月〜10月）
A2: 月別・取引先別の集計や、商品マスタとの突き合わせの練習用です。
A4: 日付 | B4: 伝票No | C4: 取引先 | D4: 商品コード | E4: 数量 | F4: 単価 | G4: 金額 | J4: 練習① 月別の売上合計（PDF No.1）
A5: 46237 | B5: S-20260803 | C5: ひだまり工業 | D5: A-101 | E5: 4 | F5: =INDEX(商品マスタ!$C$5:$C$10,MATCH(D5,商品マスタ!$A$5:$A$10,0)) -> 2800 | G5: =E5*F5 -> 11200 | J5: 2026年8月
A6: 46239 | B6: S-20260805 | C6: サンプル商事 | D6: A-102 | E6: 10 | F6: =INDEX(商品マスタ!$C$5:$C$10,MATCH(D6,商品マスタ!$A$5:$A$10,0)) -> 980 | G6: =E6*F6 -> 9800 | J6: 2026年9月
A7: 46242 | B7: S-20260808 | C7: あおぞら設計 | D7: B-201 | E7: 2 | F7: =INDEX(商品マスタ!$C$5:$C$10,MATCH(D7,商品マスタ!$A$5:$A$10,0)) -> 12800 | G7: =E7*F7 -> 25600 | J7: 2026年10月
A8: 46246 | B8: S-20260812 | C8: こもれび食品 | D8: A-103 | E8: 3 | F8: =INDEX(商品マスタ!$C$5:$C$10,MATCH(D8,商品マスタ!$A$5:$A$10,0)) -> 1500 | G8: =E8*F8 -> 4500
A9: 46252 | B9: S-20260818 | C9: ひだまり工業 | D9: B-202 | E9: 5 | F9: =INDEX(商品マスタ!$C$5:$C$10,MATCH(D9,商品マスタ!$A$5:$A$10,0)) -> 1200 | G9: =E9*F9 -> 6000 | J9: 練習② 取引先別の売上合計（PDF No.2）
A10: 46256 | B10: S-20260822 | C10: サンプル商事 | D10: C-301 | E10: 1 | F10: =INDEX(商品マスタ!$C$5:$C$10,MATCH(D10,商品マスタ!$A$5:$A$10,0)) -> 6400 | G10: =E10*F10 -> 6400 | J10: ひだまり工業
A11: 46261 | B11: S-20260827 | C11: あおぞら設計 | D11: A-101 | E11: 6 | F11: =INDEX(商品マスタ!$C$5:$C$10,MATCH(D11,商品マスタ!$A$5:$A$10,0)) -> 2800 | G11: =E11*F11 -> 16800 | J11: サンプル商事
A12: 46264 | B12: S-20260830 | C12: こもれび食品 | D12: A-102 | E12: 8 | F12: =INDEX(商品マスタ!$C$5:$C$10,MATCH(D12,商品マスタ!$A$5:$A$10,0)) -> 980 | G12: =E12*F12 -> 7840 | J12: あおぞら設計
A13: 46267 | B13: S-20260902 | C13: ひだまり工業 | D13: B-201 | E13: 1 | F13: =INDEX(商品マスタ!$C$5:$C$10,MATCH(D13,商品マスタ!$A$5:$A$10,0)) -> 12800 | G13: =E13*F13 -> 12800 | J13: こもれび食品
A14: 46271 | B14: S-20260906 | C14: サンプル商事 | D14: A-101 | E14: 5 | F14: =INDEX(商品マスタ!$C$5:$C$10,MATCH(D14,商品マスタ!$A$5:$A$10,0)) -> 2800 | G14: =E14*F14 -> 14000
A15: 46275 | B15: S-20260910 | C15: あおぞら設計 | D15: A-103 | E15: 2 | F15: =INDEX(商品マスタ!$C$5:$C$10,MATCH(D15,商品マスタ!$A$5:$A$10,0)) -> 1500 | G15: =E15*F15 -> 3000 | J15: 黄色のセルに、Claudeに作ってもらった数式を入れてみましょう。
A16: 46278 | B16: S-20260913 | C16: こもれび食品 | D16: B-202 | E16: 4 | F16: =INDEX(商品マスタ!$C$5:$C$10,MATCH(D16,商品マスタ!$A$5:$A$10,0)) -> 1200 | G16: =E16*F16 -> 4800 | J16: 答え合わせ: 3か月の合計は G列の一番下の「合計」と同じになります。
A17: 46282 | B17: S-20260917 | C17: ひだまり工業 | D17: A-102 | E17: 12 | F17: =INDEX(商品マスタ!$C$5:$C$10,MATCH(D17,商品マスタ!$A$5:$A$10,0)) -> 980 | G17: =E17*F17 -> 11760
A18: 46286 | B18: S-20260921 | C18: サンプル商事 | D18: B-201 | E18: 3 | F18: =INDEX(商品マスタ!$C$5:$C$10,MATCH(D18,商品マスタ!$A$5:$A$10,0)) -> 12800 | G18: =E18*F18 -> 38400
A19: 46289 | B19: S-20260924 | C19: あおぞら設計 | D19: C-301 | E19: 2 | F19: =INDEX(商品マスタ!$C$5:$C$10,MATCH(D19,商品マスタ!$A$5:$A$10,0)) -> 6400 | G19: =E19*F19 -> 12800
A20: 46293 | B20: S-20260928 | C20: こもれび食品 | D20: A-101 | E20: 7 | F20: =INDEX(商品マスタ!$C$5:$C$10,MATCH(D20,商品マスタ!$A$5:$A$10,0)) -> 2800 | G20: =E20*F20 -> 19600
A21: 46296 | B21: S-20261001 | C21: ひだまり工業 | D21: A-103 | E21: 6 | F21: =INDEX(商品マスタ!$C$5:$C$10,MATCH(D21,商品マスタ!$A$5:$A$10,0)) -> 1500 | G21: =E21*F21 -> 9000
A22: 46299 | B22: S-20261004 | C22: サンプル商事 | D22: B-202 | E22: 2 | F22: =INDEX(商品マスタ!$C$5:$C$10,MATCH(D22,商品マスタ!$A$5:$A$10,0)) -> 1200 | G22: =E22*F22 -> 2400
A23: 46303 | B23: S-20261008 | C23: あおぞら設計 | D23: A-102 | E23: 15 | F23: =INDEX(商品マスタ!$C$5:$C$10,MATCH(D23,商品マスタ!$A$5:$A$10,0)) -> 980 | G23: =E23*F23 -> 14700
A24: 46306 | B24: S-20261011 | C24: こもれび食品 | D24: B-201 | E24: 2 | F24: =INDEX(商品マスタ!$C$5:$C$10,MATCH(D24,商品マスタ!$A$5:$A$10,0)) -> 12800 | G24: =E24*F24 -> 25600
A25: 46310 | B25: S-20261015 | C25: ひだまり工業 | D25: C-301 | E25: 1 | F25: =INDEX(商品マスタ!$C$5:$C$10,MATCH(D25,商品マスタ!$A$5:$A$10,0)) -> 6400 | G25: =E25*F25 -> 6400
A26: 46314 | B26: S-20261019 | C26: サンプル商事 | D26: A-101 | E26: 3 | F26: =INDEX(商品マスタ!$C$5:$C$10,MATCH(D26,商品マスタ!$A$5:$A$10,0)) -> 2800 | G26: =E26*F26 -> 8400
A27: 46318 | B27: S-20261023 | C27: あおぞら設計 | D27: B-202 | E27: 6 | F27: =INDEX(商品マスタ!$C$5:$C$10,MATCH(D27,商品マスタ!$A$5:$A$10,0)) -> 1200 | G27: =E27*F27 -> 7200
A28: 46322 | B28: S-20261027 | C28: こもれび食品 | D28: A-103 | E28: 5 | F28: =INDEX(商品マスタ!$C$5:$C$10,MATCH(D28,商品マスタ!$A$5:$A$10,0)) -> 1500 | G28: =E28*F28 -> 7500
D29: 数量合計 | E29: =SUM(E5:E28) -> 114 | F29: 合計 | G29: =SUM(G5:G28) -> 286500

Sheet 経費精算
A1: 経費精算一覧（2026年10月分）
A2: 科目別の集計や、申請内容のチェックの練習用です。
A4: 申請日 | B4: 申請者 | C4: 勘定科目 | D4: 内容 | E4: 金額 | F4: 領収書 | H4: 練習③ 勘定科目別の合計（PDF No.2）
A5: 46296 | B5: 佐藤 | C5: 旅費交通費 | D5: 客先訪問 電車代 | E5: 640 | F5: あり | H5: 旅費交通費
A6: 46297 | B6: 鈴木 | C6: 消耗品費 | D6: プリンター用紙 | E6: 1980 | F6: あり | H6: 消耗品費
A7: 46298 | B7: 高橋 | C7: 会議費 | D7: 打ち合わせ コーヒー代 | E7: 1320 | F7: あり | H7: 会議費
A8: 46301 | B8: 佐藤 | C8: 旅費交通費 | D8: 客先訪問 バス代 | E8: 460 | F8: あり | H8: 通信費
A9: 46302 | B9: 田中 | C9: 通信費 | D9: 切手代 | E9: 840 | F9: あり
A10: 46303 | B10: 鈴木 | C10: 旅費交通費 | D10: 研修会場 電車代 | E10: 720 | F10: あり
A11: 46304 | B11: 高橋 | C11: 消耗品費 | D11: USBメモリ | E11: 1580 | F11: なし
A12: 46305 | B12: 田中 | C12: 旅費交通費 | D12: 客先訪問 電車代 | E12: 48000 | F12: あり
A13: 46309 | B13: 佐藤 | C13: 会議費 | D13: 来客用お茶菓子 | E13: 2160 | F13: あり
A14: 46310 | B14: 鈴木 | C14: 旅費交通費 | D14: 研修会場 電車代 | E14: 720 | F14: あり
A15: 46310 | B15: 鈴木 | C15: 旅費交通費 | D15: 研修会場 電車代 | E15: 720 | F15: あり
A16: 46311 | B16: 高橋 | C16: 通信費 | D16: レターパック | E16: 1200 | F16: あり
A17: 46315 | B17: 田中 | C17: 消耗品費 | D17: 電池 | E17: 650 | F17: あり
A18: 46316 | B18: 佐藤 | C18: 旅費交通費 | D18: 客先訪問 タクシー代 | E18: 2380 | F18: あり
A19: 46318 | B19: 鈴木 | C19: 会議費 | D19: 打ち合わせ 昼食代 | E19: 3300 | F19: あり
A20: 46322 | B20: 高橋 | C20: 旅費交通費 | D20: 客先訪問 電車代 | E20: 580 | F20: あり
D21: 合計 | E21: =SUM(E5:E20) -> 67250

Sheet 取引先リスト
A1: 取引先リスト（表記ゆれあり）
A2: 同じ会社がちがう書き方で登録されています。統一と重複チェックの練習用です。
A4: 取引先ID | B4: 取引先名 | C4: 電話番号 | E4: 統一後の名前（練習④ PDF No.10・11）
A5: V001 | B5: 株式会社ひだまり工業 | C5: 03-1234-5678
A6: V002 | B6: (株)ひだまり工業 | C6: 03-1234-5678
A7: V003 | B7: サンプル商事株式会社 | C7: 06-2345-6789
A8: V004 | B8: ｻﾝﾌﾟﾙ商事（株） | C8: 06-2345-6789
A9: V005 | B9: 有限会社あおぞら設計 | C9: 045-345-6789
A10: V006 | B10: あおぞら設計 | C10: 045-345-6789
A11: V007 | B11: 株式会社こもれび食品 | C11: 052-456-7890
A12: V008 | B12: 株式会社 こもれび食品 | C12: 052-456-7890
A13: V009 | B13: 合同会社ひなた印刷 | C13: 011-567-8901
A14: V010 | B14: ＡＢＣ物流株式会社 | C14: 092-678-9012
A15: V011 | B15: ABC物流（株） | C15: 092-678-9012
A16: V012 | B16: 株式会社みどり不動産 | C16: 03-7890-1234
E18: ヒント: 電話番号が同じなら、同じ会社の可能性が高いです。

Sheet 請求と入金
A1: 請求と入金の照合（2026年9月請求分）
A2: 左が請求一覧、右が通帳の入金一覧です。入金もれ・金額ちがいを探す練習用です。
A4: 請求No | B4: 取引先 | C4: 請求額 | D4: 支払期日 | F4: 入金日 | G4: 振込名義 | H4: 入金額
A5: INV-0901 | B5: ひだまり工業 | C5: 132000 | D5: 46326 | F5: 46319 | G5: ﾋﾀﾞﾏﾘｺｳｷﾞﾖｳ(ｶ | H5: 132000
A6: INV-0902 | B6: サンプル商事 | C6: 85800 | D6: 46326 | F6: 46323 | G6: ｻﾝﾌﾟﾙｼﾖｳｼﾞ(ｶ | H6: 85140
A7: INV-0903 | B7: あおぞら設計 | C7: 47300 | D7: 46326 | F7: 46325 | G7: ｺﾓﾚﾋﾞｼﾖｸﾋﾝ(ｶ | H7: 210100
A8: INV-0904 | B8: こもれび食品 | C8: 210100 | D8: 46326 | F8: 46325 | G8: ﾋﾅﾀｲﾝｻﾂ(ﾄﾞ | H8: 19800
A9: INV-0905 | B9: ひなた印刷 | C9: 19800 | D9: 46326
A11: 照合結果（練習⑤ PDF No.14）
A12: 請求No | B12: 入金状況 | C12: 差額 | D12: メモ
A19: ヒント: 入金一覧に名前がない会社と、金額が合わない会社がそれぞれ1社あります。
